dj_elasticsearch_flex-0.3.3.dist-info/DESCRIPTION.rst
dj_elasticsearch_flex-0.3.3.dist-info/METADATA
dj_elasticsearch_flex-0.3.3.dist-info/RECORD
dj_elasticsearch_flex-0.3.3.dist-info/WHEEL
dj_elasticsearch_flex-0.3.3.dist-info/metadata.json
dj_elasticsearch_flex-0.3.3.dist-info/top_level.txt
elasticsearch_flex/__init__.py
elasticsearch_flex/analysis_utils.py
elasticsearch_flex/apps.py
elasticsearch_flex/dispatchers.py
elasticsearch_flex/fields.py
elasticsearch_flex/indexes.py
elasticsearch_flex/query.py
elasticsearch_flex/search_templates.py
elasticsearch_flex/signals.py
elasticsearch_flex/tasks.py
elasticsearch_flex/utils.py
elasticsearch_flex/management/__init__.py
elasticsearch_flex/management/commands/__init__.py
elasticsearch_flex/management/commands/flex_sync.py
elasticsearch_flex/management/commands/flex_update_index.py
