Metadata-Version: 2.0
Name: dj-elasticsearch-flex
Version: 0.3.3
Summary: Elasticsearch for Django which lets you do stuff.
Home-page: https://github.com/prashnts/dj-elasticsearch-flex
Author: Prashant Sinha
Author-email: prashant+git@noop.pw
License: MIT
Keywords: dj-elasticsearch-flex
Platform: UNKNOWN
Classifier: Development Status :: 3 - Alpha
Classifier: Framework :: Django
Classifier: Framework :: Django :: 1.8
Classifier: Framework :: Django :: 1.9
Classifier: Framework :: Django :: 1.10
Classifier: Intended Audience :: Developers
Classifier: License :: OSI Approved :: BSD License
Classifier: Natural Language :: English
Classifier: Programming Language :: Python :: 2
Classifier: Programming Language :: Python :: 2.7
Classifier: Programming Language :: Python :: 3
Classifier: Programming Language :: Python :: 3.2
Classifier: Programming Language :: Python :: 3.3
Classifier: Programming Language :: Python :: 3.4
Classifier: Programming Language :: Python :: 3.5
